ingesture/__init__.py
ingesture/exceptions.py
ingesture/export/__init__.py
ingesture/export/nwb/__init__.py
ingesture/export/nwb/container.py
ingesture/fields/__init__.py
ingesture/fields/base.py
ingesture/fields/link.py
ingesture/fields/video.py
ingesture/schema/__init__.py
ingesture/schema/base.py
ingesture/spec/__init__.py
ingesture/spec/base.py
ingesture/spec/file.py
ingesture/spec/path.py
ingesture/utils.py
ingesture-0.1.0.dist-info/LICENSE
ingesture-0.1.0.dist-info/WHEEL
ingesture-0.1.0.dist-info/METADATA
ingesture-0.1.0.dist-info/RECORD
