Metadata-Version: 2.1
Name: ingesture
Version: 0.1.0
Summary: Ingest gesturally-structured data into models with multiple export
Home-page: https://github.com/auto-pi-lot/ingest
License: MPL-2.0
Author: sneakers-the-rat
Author-email: JLSaunders987@gmail.com
Requires-Python: >=3.9,<3.11
Classifier: License :: OSI Approved
Classifier: Programming Language :: Python :: 3
Classifier: Programming Language :: Python :: 3.10
Classifier: Programming Language :: Python :: 3.9
Provides-Extra: docs
Provides-Extra: nwb
Requires-Dist: PyYAML (>=6.0,<7.0)
Requires-Dist: Sphinx (>=4.4.0,<5.0.0); extra == "docs"
Requires-Dist: furo (>=2022.3.4,<2023.0.0); extra == "docs"
Requires-Dist: pandas (>=1.1,<2.0)
Requires-Dist: parse (>=1.19.0,<2.0.0)
Requires-Dist: pydantic (>=1.9.0,<2.0.0)
Requires-Dist: pynwb (>=2.5.1,<3.0.0); extra == "nwb"
Requires-Dist: scipy (>=1.8.0,<2.0.0)
Project-URL: Repository, https://github.com/auto-pi-lot/ingest
